upathtools/__init__.py
upathtools/async_helpers.py
upathtools/async_ops.py
upathtools/async_upath.py
upathtools/cli_ops.py
upathtools/cli_parser.py
upathtools/common_types.py
upathtools/core.py
upathtools/filesystems/__init__.py
upathtools/filesystems/async_local_fs.py
upathtools/filesystems/auto_expand_fs.py
upathtools/filesystems/base/__init__.py
upathtools/filesystems/base/basefilesystem.py
upathtools/filesystems/base/baseupath.py
upathtools/filesystems/base/file_objects.py
upathtools/filesystems/base/filefilesystem.py
upathtools/filesystems/base/wrapper.py
upathtools/filesystems/basemodel_fs.py
upathtools/filesystems/basemodel_instance_fs.py
upathtools/filesystems/combining_filesystems/__init__.py
upathtools/filesystems/combining_filesystems/flat_union_fs.py
upathtools/filesystems/combining_filesystems/overlay_fs.py
upathtools/filesystems/combining_filesystems/union_fs.py
upathtools/filesystems/delegating_fs.py
upathtools/filesystems/distribution_fs.py
upathtools/filesystems/file_filesystems/__init__.py
upathtools/filesystems/file_filesystems/jsonschema_fs.py
upathtools/filesystems/file_filesystems/markdown_fs.py
upathtools/filesystems/file_filesystems/openapi_fs.py
upathtools/filesystems/file_filesystems/sqlite_fs.py
upathtools/filesystems/file_filesystems/treesitter_fs.py
upathtools/filesystems/fsspec_filesystems/__init__.py
upathtools/filesystems/fsspec_filesystems/azure.py
upathtools/filesystems/fsspec_filesystems/gcs.py
upathtools/filesystems/fsspec_filesystems/hdfs.py
upathtools/filesystems/fsspec_filesystems/hf.py
upathtools/filesystems/fsspec_filesystems/s3.py
upathtools/filesystems/fsspec_filesystems/sftp.py
upathtools/filesystems/fsspec_filesystems/smb.py
upathtools/filesystems/fsspec_filesystems/webdav.py
upathtools/filesystems/httpx_fs.py
upathtools/filesystems/isolated_memory_fs.py
upathtools/filesystems/package_fs.py
upathtools/filesystems/remote_filesystems/__init__.py
upathtools/filesystems/remote_filesystems/appwrite_fs.py
upathtools-1.18.12.dist-info/licenses/LICENSE
upathtools-1.18.12.dist-info/WHEEL
upathtools-1.18.12.dist-info/entry_points.txt
upathtools-1.18.12.dist-info/METADATA
upathtools-1.18.12.dist-info/RECORD
