Metadata-Version: 2.4
Name: upathtools
Version: 1.18.12
Summary: UPath utilities
Keywords: 
Author: Philipp Temminghoff
Author-email: Philipp Temminghoff <philipptemminghoff@googlemail.com>
License-Expression: MIT
License-File: LICENSE
Classifier: Development Status :: 4 - Beta
Classifier: Intended Audience :: Developers
Classifier: Operating System :: OS Independent
Classifier: Programming Language :: Python :: 3
Classifier: Programming Language :: Python :: 3 :: Only
Classifier: Programming Language :: Python :: 3.12
Classifier: Programming Language :: Python :: 3.13
Classifier: Programming Language :: Python :: 3.14
Classifier: Topic :: Documentation
Classifier: Topic :: Software Development
Classifier: Topic :: Utilities
Classifier: Typing :: Typed
Requires-Dist: aiofile>=3.9.0
Requires-Dist: fsspec>=2025.2.0
Requires-Dist: python-dotenv>=1.0.0
Requires-Dist: ripgrep-rs>=0.3.14
Requires-Dist: universal-pathlib>=0.2.6
Requires-Dist: appwrite ; extra == 'appwrite'
Requires-Dist: beam-client>=0.2.187 ; (python_full_version < '3.14' and extra == 'beam') or (sys_platform != 'win32' and extra == 'beam')
Requires-Dist: daytona ; python_full_version < '3.14' and extra == 'daytona'
Requires-Dist: e2b-code-interpreter ; extra == 'e2b'
Requires-Dist: python-gitlab>=7.0.0 ; extra == 'gitlab'
Requires-Dist: httpx ; extra == 'httpx'
Requires-Dist: yarl ; extra == 'httpx'
Requires-Dist: brotli ; extra == 'httpx'
Requires-Dist: fastmcp ; extra == 'mcp'
Requires-Dist: mcp ; extra == 'mcp'
Requires-Dist: microsandbox ; extra == 'microsandbox'
Requires-Dist: modal ; extra == 'modal'
Requires-Dist: notion-client ; extra == 'notion-client'
Requires-Dist: openapi3 ; extra == 'openapi3'
Requires-Dist: sqlalchemy[aiosqlite] ; extra == 'sqlite'
Requires-Dist: tree-sitter>=0.25.2 ; extra == 'tree-sitter'
Requires-Dist: tree-sitter-python>=0.25.0 ; extra == 'tree-sitter'
Requires-Dist: tree-sitter-c>=0.24.1 ; extra == 'tree-sitter'
Requires-Dist: tree-sitter-javascript>=0.25.0 ; extra == 'tree-sitter'
Requires-Dist: tree-sitter>=0.25.2 ; extra == 'tree-sitter'
Requires-Dist: tree-sitter-typescript>=0.23.0 ; extra == 'tree-sitter'
Requires-Dist: tree-sitter-cpp>=0.23.0 ; extra == 'tree-sitter'
Requires-Dist: tree-sitter-rust>=0.23.0 ; extra == 'tree-sitter'
Requires-Dist: tree-sitter-go>=0.23.0 ; extra == 'tree-sitter'
Requires-Dist: tree-sitter-json>=0.24.0 ; extra == 'tree-sitter'
Requires-Dist: tree-sitter-yaml>=0.6.0 ; extra == 'tree-sitter'
Requires-Dist: vercel ; extra == 'vercel'
Requires-Python: >=3.13
Project-URL: Code coverage, https://app.codecov.io/gh/phil65/upathtools
Project-URL: Discussions, https://github.com/phil65/upathtools/discussions
Project-URL: Documentation, https://phil65.github.io/upathtools/
Project-URL: Issues, https://github.com/phil65/upathtools/issues
Project-URL: Source, https://github.com/phil65/upathtools
Provides-Extra: appwrite
Provides-Extra: beam
Provides-Extra: daytona
Provides-Extra: e2b
Provides-Extra: gitlab
Provides-Extra: httpx
Provides-Extra: mcp
Provides-Extra: microsandbox
Provides-Extra: modal
Provides-Extra: notion-client
Provides-Extra: openapi3
Provides-Extra: sqlite
Provides-Extra: tree-sitter
Provides-Extra: vercel
